README.rst
setup.py
bin/lumper
lumper/__init__.py
lumper/log_setter.py
lumper.egg-info/PKG-INFO
lumper.egg-info/SOURCES.txt
lumper.egg-info/dependency_links.txt
lumper.egg-info/requires.txt
lumper.egg-info/top_level.txt
lumper/mailer/__init__.py
lumper/mailer/on_build.py
lumper/modes/__init__.py
lumper/modes/mailer.py
lumper/modes/server.py
lumper/modes/worker.py
lumper/server/__init__.py
lumper/server/json_handler.py
lumper/server/handlers/__init__.py
lumper/server/handlers/heartbeat.py
lumper/server/handlers/webhook.py
lumper/worker/__init__.py
lumper/worker/build.py
lumper/worker/heartbeat.py