Metadata-Version: 1.1
Name: lumper
Version: 0.2.18
Summary: Containers builder for docker.
Home-page: http://github.com/mosquito/lumper
Author: Dmitry Orlov <me@mosquito.su>
Author-email: me@mosquito.su
License: MIT
Platform: all
Classifier: Environment :: Console
Classifier: Programming Language :: Python
